{
    "points": [
        {
            "x": 229,
            "y": 305,
            "labe": "a"
        },
        {
            "x": 482,
            "y": 43,
            "labe": "b"
        },
        {
            "x": 252,
            "y": 58,
            "labe": "c"
        },
        {
            "x": 511,
            "y": 327,
            "labe": "d"
        },
        {
            "x": 360,
            "y": 170,
            "labe": "e"
        },
        {
            "x": 181,
            "y": 226,
            "labe": "f"
        },
        {
            "x": 362,
            "y": 214,
            "labe": "g"
        }
    ],
    "lines": [
        {
            "start": {
                "x": 360,
                "y": 170,
                "labe": "e"
            },
            "end": {
                "x": 511,
                "y": 327,
                "labe": "d"
            }
        },
        {
            "start": {
                "x": 252,
                "y": 58,
                "labe": "c"
            },
            "end": {
                "x": 360,
                "y": 170,
                "labe": "e"
            }
        },
        {
            "start": {
                "x": 360,
                "y": 170,
                "labe": "e"
            },
            "end": {
                "x": 482,
                "y": 43,
                "labe": "b"
            }
        },
        {
            "start": {
                "x": 229,
                "y": 305,
                "labe": "a"
            },
            "end": {
                "x": 360,
                "y": 170,
                "labe": "e"
            }
        },
        {
            "start": {
                "x": 181,
                "y": 226,
                "labe": "f"
            },
            "end": {
                "x": 360,
                "y": 170,
                "labe": "e"
            }
        },
        {
            "start": {
                "x": 360,
                "y": 170,
                "labe": "e"
            },
            "end": {
                "x": 362,
                "y": 214,
                "labe": "g"
            }
        }
    ],
    "angles": [
        {
            "value": "88",
            "leftline": {
                "start": {
                    "x": 360,
                    "y": 170,
                    "labe": "e"
                },
                "end": {
                    "x": 482,
                    "y": 43,
                    "labe": "b"
                }
            },
            "rightline": {
                "start": {
                    "x": 360,
                    "y": 170,
                    "labe": "e"
                },
                "end": {
                    "x": 511,
                    "y": 327,
                    "labe": "d"
                }
            }
        },
        {
            "value": "88",
            "leftline": {
                "start": {
                    "x": 229,
                    "y": 305,
                    "labe": "a"
                },
                "end": {
                    "x": 360,
                    "y": 170,
                    "labe": "e"
                }
            },
            "rightline": {
                "start": {
                    "x": 360,
                    "y": 170,
                    "labe": "e"
                },
                "end": {
                    "x": 511,
                    "y": 327,
                    "labe": "d"
                }
            }
        },
        {
            "value": "63",
            "leftline": {
                "start": {
                    "x": 181,
                    "y": 226,
                    "labe": "f"
                },
                "end": {
                    "x": 360,
                    "y": 170,
                    "labe": "e"
                }
            },
            "rightline": {
                "start": {
                    "x": 360,
                    "y": 170,
                    "labe": "e"
                },
                "end": {
                    "x": 511,
                    "y": 327,
                    "labe": "d"
                }
            }
        },
        {
            "value": "41",
            "leftline": {
                "start": {
                    "x": 360,
                    "y": 170,
                    "labe": "e"
                },
                "end": {
                    "x": 362,
                    "y": 214,
                    "labe": "g"
                }
            },
            "rightline": {
                "start": {
                    "x": 360,
                    "y": 170,
                    "labe": "e"
                },
                "end": {
                    "x": 511,
                    "y": 327,
                    "labe": "d"
                }
            }
        },
        {
            "value": "88",
            "leftline": {
                "start": {
                    "x": 360,
                    "y": 170,
                    "labe": "e"
                },
                "end": {
                    "x": 482,
                    "y": 43,
                    "labe": "b"
                }
            },
            "rightline": {
                "start": {
                    "x": 252,
                    "y": 58,
                    "labe": "c"
                },
                "end": {
                    "x": 360,
                    "y": 170,
                    "labe": "e"
                }
            }
        },
        {
            "value": "88",
            "leftline": {
                "start": {
                    "x": 229,
                    "y": 305,
                    "labe": "a"
                },
                "end": {
                    "x": 360,
                    "y": 170,
                    "labe": "e"
                }
            },
            "rightline": {
                "start": {
                    "x": 252,
                    "y": 58,
                    "labe": "c"
                },
                "end": {
                    "x": 360,
                    "y": 170,
                    "labe": "e"
                }
            }
        },
        {
            "value": "63",
            "leftline": {
                "start": {
                    "x": 181,
                    "y": 226,
                    "labe": "f"
                },
                "end": {
                    "x": 360,
                    "y": 170,
                    "labe": "e"
                }
            },
            "rightline": {
                "start": {
                    "x": 252,
                    "y": 58,
                    "labe": "c"
                },
                "end": {
                    "x": 360,
                    "y": 170,
                    "labe": "e"
                }
            }
        },
        {
            "value": "41",
            "leftline": {
                "start": {
                    "x": 360,
                    "y": 170,
                    "labe": "e"
                },
                "end": {
                    "x": 362,
                    "y": 214,
                    "labe": "g"
                }
            },
            "rightline": {
                "start": {
                    "x": 252,
                    "y": 58,
                    "labe": "c"
                },
                "end": {
                    "x": 360,
                    "y": 170,
                    "labe": "e"
                }
            }
        },
        {
            "value": "29",
            "leftline": {
                "start": {
                    "x": 181,
                    "y": 226,
                    "labe": "f"
                },
                "end": {
                    "x": 360,
                    "y": 170,
                    "labe": "e"
                }
            },
            "rightline": {
                "start": {
                    "x": 360,
                    "y": 170,
                    "labe": "e"
                },
                "end": {
                    "x": 482,
                    "y": 43,
                    "labe": "b"
                }
            }
        },
        {
            "value": "46",
            "leftline": {
                "start": {
                    "x": 360,
                    "y": 170,
                    "labe": "e"
                },
                "end": {
                    "x": 362,
                    "y": 214,
                    "labe": "g"
                }
            },
            "rightline": {
                "start": {
                    "x": 360,
                    "y": 170,
                    "labe": "e"
                },
                "end": {
                    "x": 482,
                    "y": 43,
                    "labe": "b"
                }
            }
        },
        {
            "value": "28",
            "leftline": {
                "start": {
                    "x": 181,
                    "y": 226,
                    "labe": "f"
                },
                "end": {
                    "x": 360,
                    "y": 170,
                    "labe": "e"
                }
            },
            "rightline": {
                "start": {
                    "x": 229,
                    "y": 305,
                    "labe": "a"
                },
                "end": {
                    "x": 360,
                    "y": 170,
                    "labe": "e"
                }
            }
        },
        {
            "value": "47",
            "leftline": {
                "start": {
                    "x": 360,
                    "y": 170,
                    "labe": "e"
                },
                "end": {
                    "x": 362,
                    "y": 214,
                    "labe": "g"
                }
            },
            "rightline": {
                "start": {
                    "x": 229,
                    "y": 305,
                    "labe": "a"
                },
                "end": {
                    "x": 360,
                    "y": 170,
                    "labe": "e"
                }
            }
        },
        {
            "value": "75",
            "leftline": {
                "start": {
                    "x": 360,
                    "y": 170,
                    "labe": "e"
                },
                "end": {
                    "x": 362,
                    "y": 214,
                    "labe": "g"
                }
            },
            "rightline": {
                "start": {
                    "x": 181,
                    "y": 226,
                    "labe": "f"
                },
                "end": {
                    "x": 360,
                    "y": 170,
                    "labe": "e"
                }
            }
        }
    ]
}